{
 "__fileName__": "base/meta/MarkerSet/Cave_Flooded_TR8_EW_01 (Merged).mrk",
 "__snoID__": 403127,
 "__type__": "MarkerSetDefinition",
 "__typeHash__": 4093179991,
 "tMarkerSet": [
  {
   "__type__": "Marker",
   "__typeHash__": 3132676386,
   "dwHash": 3636573002,
   "nID": 432,
   "eType": 0,
   "transform": {
    "__type__": "PRTransform",
    "__typeHash__": 2588169118,
    "q": {
     "__type__": "bcQuat",
     "__typeHash__": 3955716320,
     "x": -0.2722248435020447,
     "y": 0.1358092874288559,
     "z": 0.9439560770988464,
     "w": 0.12804833054542542
    },
    "wp": {
     "x": 18.850200653076172,
     "y": 2.80115008354187,
     "z": 8.39564037322998
    }
   },
   "snoname": {
    "__raw__": 457255,
    "__group__": 57,
    "__type__": "DT_SNO_NAME",
    "__typeHash__": 3339108615,
    "__targetFileName__": "base/meta/Material/Cave_Flooded_Mold_Tendrils_B.mat",
    "groupName": "Material",
    "name": "Cave_Flooded_Mold_Tendrils_B"
   },
   "dwMarkerFlags": 1024,
   "dwMarkerFlagsEx": 0,
   "vecScale": {
    "x": 1.2200000286102295,
    "y": 1.2200000286102295,
    "z": 1.2200000286102295
   },
   "ptBase": [
    {
     "__type__": "MarkerDecalData",
     "__typeHash__": 2650697781,
     "dwType": 2650697781,
     "dwPad": 0,
     "dwMarkerDecalFlags": 0,
     "flAngleThreshold": 3.1415927410125732,
     "unk_18f0908": 0,
     "bDieOverride": false,
     "ptRunTimeMaterialValues": []
    }
   ],
   "ptGroupData": [],
   "ptMarkerLinks": [],
   "unk_c339f69": -1,
   "dwSeed": 0,
   "tPrefabData": {
    "__type__": "PrefabData",
    "__typeHash__": 3988626058,
    "dwFlags": 0,
    "eOverrideFadeSettings": 0,
    "eFadeMethod": 0,
    "nFadeGroup": 0,
    "unk_d094b9a": 0,
    "eCullingLevel": 0,
    "szLookOverride": 0,
    "dwShaderMapOverride": 4294967295,
    "ptRunTimeMaterialValues": []
   }
  },
  {
   "__type__": "Marker",
   "__typeHash__": 3132676386,
   "dwHash": 3636573003,
   "nID": 433,
   "eType": 0,
   "transform": {
    "__type__": "PRTransform",
    "__typeHash__": 2588169118,
    "q": {
     "__type__": "bcQuat",
     "__typeHash__": 3955716320,
     "x": 0.00013704076991416514,
     "y": -0.12593242526054382,
     "z": 0.9086323976516724,
     "w": 0.3981561064720154
    },
    "wp": {
     "x": 17.210599899291992,
     "y": 8.95658016204834,
     "z": 6.756340026855469
    }
   },
   "snoname": {
    "__raw__": 457255,
    "__group__": 57,
    "__type__": "DT_SNO_NAME",
    "__typeHash__": 3339108615,
    "__targetFileName__": "base/meta/Material/Cave_Flooded_Mold_Tendrils_B.mat",
    "groupName": "Material",
    "name": "Cave_Flooded_Mold_Tendrils_B"
   },
   "dwMarkerFlags": 1024,
   "dwMarkerFlagsEx": 0,
   "vecScale": {
    "x": 1.2200000286102295,
    "y": 1.2200000286102295,
    "z": 1.2200000286102295
   },
   "ptBase": [
    {
     "__type__": "MarkerDecalData",
     "__typeHash__": 2650697781,
     "dwType": 2650697781,
     "dwPad": 0,
     "dwMarkerDecalFlags": 0,
     "flAngleThreshold": 3.1415927410125732,
     "unk_18f0908": 0,
     "bDieOverride": false,
     "ptRunTimeMaterialValues": []
    }
   ],
   "ptGroupData": [],
   "ptMarkerLinks": [],
   "unk_c339f69": -1,
   "dwSeed": 0,
   "tPrefabData": {
    "__type__": "PrefabData",
    "__typeHash__": 3988626058,
    "dwFlags": 0,
    "eOverrideFadeSettings": 0,
    "eFadeMethod": 0,
    "nFadeGroup": 0,
    "unk_d094b9a": 0,
    "eCullingLevel": 0,
    "szLookOverride": 0,
    "dwShaderMapOverride": 4294967295,
    "ptRunTimeMaterialValues": []
   }
  },
  {
   "__type__": "Marker",
   "__typeHash__": 3132676386,
   "dwHash": 3636573004,
   "nID": 434,
   "eType": 0,
   "transform": {
    "__type__": "PRTransform",
    "__typeHash__": 2588169118,
    "q": {
     "__type__": "bcQuat",
     "__typeHash__": 3955716320,
     "x": -0.05153726413846016,
     "y": 0.20474950969219208,
     "z": 0.9540219306945801,
     "w": 0.21275319159030914
    },
    "wp": {
     "x": 16.815399169921875,
     "y": 10.165900230407715,
     "z": 7.120480060577393
    }
   },
   "snoname": {
    "__raw__": 457255,
    "__group__": 57,
    "__type__": "DT_SNO_NAME",
    "__typeHash__": 3339108615,
    "__targetFileName__": "base/meta/Material/Cave_Flooded_Mold_Tendrils_B.mat",
    "groupName": "Material",
    "name": "Cave_Flooded_Mold_Tendrils_B"
   },
   "dwMarkerFlags": 1024,
   "dwMarkerFlagsEx": 0,
   "vecScale": {
    "x": 1.0399999618530273,
    "y": 1.0399999618530273,
    "z": 1.0399999618530273
   },
   "ptBase": [
    {
     "__type__": "MarkerDecalData",
     "__typeHash__": 2650697781,
     "dwType": 2650697781,
     "dwPad": 0,
     "dwMarkerDecalFlags": 0,
     "flAngleThreshold": 3.1415927410125732,
     "unk_18f0908": 0,
     "bDieOverride": false,
     "ptRunTimeMaterialValues": []
    }
   ],
   "ptGroupData": [],
   "ptMarkerLinks": [],
   "unk_c339f69": -1,
   "dwSeed": 0,
   "tPrefabData": {
    "__type__": "PrefabData",
    "__typeHash__": 3988626058,
    "dwFlags": 0,
    "eOverrideFadeSettings": 0,
    "eFadeMethod": 0,
    "nFadeGroup": 0,
    "unk_d094b9a": 0,
    "eCullingLevel": 0,
    "szLookOverride": 0,
    "dwShaderMapOverride": 4294967295,
    "ptRunTimeMaterialValues": []
   }
  },
  {
   "__type__": "Marker",
   "__typeHash__": 3132676386,
   "dwHash": 3636573005,
   "nID": 435,
   "eType": 0,
   "transform": {
    "__type__": "PRTransform",
    "__typeHash__": 2588169118,
    "q": {
     "__type__": "bcQuat",
     "__typeHash__": 3955716320,
     "x": 0.2421625405550003,
     "y": -0.0074662924744188786,
     "z": 0.8276326060295105,
     "w": 0.5062864422798157
    },
    "wp": {
     "x": 11.9266996383667,
     "y": 9.783080101013184,
     "z": 8.500619888305664
    }
   },
   "snoname": {
    "__raw__": 457255,
    "__group__": 57,
    "__type__": "DT_SNO_NAME",
    "__typeHash__": 3339108615,
    "__targetFileName__": "base/meta/Material/Cave_Flooded_Mold_Tendrils_B.mat",
    "groupName": "Material",
    "name": "Cave_Flooded_Mold_Tendrils_B"
   },
   "dwMarkerFlags": 1024,
   "dwMarkerFlagsEx": 0,
   "vecScale": {
    "x": 1.2200000286102295,
    "y": 1.2200000286102295,
    "z": 1.2200000286102295
   },
   "ptBase": [
    {
     "__type__": "MarkerDecalData",
     "__typeHash__": 2650697781,
     "dwType": 2650697781,
     "dwPad": 0,
     "dwMarkerDecalFlags": 0,
     "flAngleThreshold": 3.1415927410125732,
     "unk_18f0908": 0,
     "bDieOverride": false,
     "ptRunTimeMaterialValues": []
    }
   ],
   "ptGroupData": [],
   "ptMarkerLinks": [],
   "unk_c339f69": -1,
   "dwSeed": 0,
   "tPrefabData": {
    "__type__": "PrefabData",
    "__typeHash__": 3988626058,
    "dwFlags": 0,
    "eOverrideFadeSettings": 0,
    "eFadeMethod": 0,
    "nFadeGroup": 0,
    "unk_d094b9a": 0,
    "eCullingLevel": 0,
    "szLookOverride": 0,
    "dwShaderMapOverride": 4294967295,
    "ptRunTimeMaterialValues": []
   }
  },
  {
   "__type__": "Marker",
   "__typeHash__": 3132676386,
   "dwHash": 3636573006,
   "nID": 436,
   "eType": 0,
   "transform": {
    "__type__": "PRTransform",
    "__typeHash__": 2588169118,
    "q": {
     "__type__": "bcQuat",
     "__typeHash__": 3955716320,
     "x": -0.004444453865289688,
     "y": 0.19679595530033112,
     "z": 0.9308997392654419,
     "w": 0.30769699811935425
    },
    "wp": {
     "x": 11.459400177001953,
     "y": 7.4789299964904785,
     "z": 8.50059986114502
    }
   },
   "snoname": {
    "__raw__": 457255,
    "__group__": 57,
    "__type__": "DT_SNO_NAME",
    "__typeHash__": 3339108615,
    "__targetFileName__": "base/meta/Material/Cave_Flooded_Mold_Tendrils_B.mat",
    "groupName": "Material",
    "name": "Cave_Flooded_Mold_Tendrils_B"
   },
   "dwMarkerFlags": 1024,
   "dwMarkerFlagsEx": 0,
   "vecScale": {
    "x": 1.2200000286102295,
    "y": 1.2200000286102295,
    "z": 1.2200000286102295
   },
   "ptBase": [
    {
     "__type__": "MarkerDecalData",
     "__typeHash__": 2650697781,
     "dwType": 2650697781,
     "dwPad": 0,
     "dwMarkerDecalFlags": 0,
     "flAngleThreshold": 3.1415927410125732,
     "unk_18f0908": 0,
     "bDieOverride": false,
     "ptRunTimeMaterialValues": []
    }
   ],
   "ptGroupData": [],
   "ptMarkerLinks": [],
   "unk_c339f69": -1,
   "dwSeed": 0,
   "tPrefabData": {
    "__type__": "PrefabData",
    "__typeHash__": 3988626058,
    "dwFlags": 0,
    "eOverrideFadeSettings": 0,
    "eFadeMethod": 0,
    "nFadeGroup": 0,
    "unk_d094b9a": 0,
    "eCullingLevel": 0,
    "szLookOverride": 0,
    "dwShaderMapOverride": 4294967295,
    "ptRunTimeMaterialValues": []
   }
  },
  {
   "__type__": "Marker",
   "__typeHash__": 3132676386,
   "dwHash": 3636573007,
   "nID": 437,
   "eType": 0,
   "transform": {
    "__type__": "PRTransform",
    "__typeHash__": 2588169118,
    "q": {
     "__type__": "bcQuat",
     "__typeHash__": 3955716320,
     "x": 0.15742962062358856,
     "y": 0.22683905065059662,
     "z": 0.8851009607315063,
     "w": 0.37464165687561035
    },
    "wp": {
     "x": 12.57450008392334,
     "y": 2.7321600914001465,
     "z": 9.904780387878418
    }
   },
   "snoname": {
    "__raw__": 457255,
    "__group__": 57,
    "__type__": "DT_SNO_NAME",
    "__typeHash__": 3339108615,
    "__targetFileName__": "base/meta/Material/Cave_Flooded_Mold_Tendrils_B.mat",
    "groupName": "Material",
    "name": "Cave_Flooded_Mold_Tendrils_B"
   },
   "dwMarkerFlags": 1024,
   "dwMarkerFlagsEx": 0,
   "vecScale": {
    "x": 1.2200000286102295,
    "y": 1.2200000286102295,
    "z": 1.2200000286102295
   },
   "ptBase": [
    {
     "__type__": "MarkerDecalData",
     "__typeHash__": 2650697781,
     "dwType": 2650697781,
     "dwPad": 0,
     "dwMarkerDecalFlags": 0,
     "flAngleThreshold": 3.1415927410125732,
     "unk_18f0908": 0,
     "bDieOverride": false,
     "ptRunTimeMaterialValues": []
    }
   ],
   "ptGroupData": [],
   "ptMarkerLinks": [],
   "unk_c339f69": -1,
   "dwSeed": 0,
   "tPrefabData": {
    "__type__": "PrefabData",
    "__typeHash__": 3988626058,
    "dwFlags": 0,
    "eOverrideFadeSettings": 0,
    "eFadeMethod": 0,
    "nFadeGroup": 0,
    "unk_d094b9a": 0,
    "eCullingLevel": 0,
    "szLookOverride": 0,
    "dwShaderMapOverride": 4294967295,
    "ptRunTimeMaterialValues": []
   }
  },
  {
   "__type__": "Marker",
   "__typeHash__": 3132676386,
   "dwHash": 3636573008,
   "nID": 438,
   "eType": 0,
   "transform": {
    "__type__": "PRTransform",
    "__typeHash__": 2588169118,
    "q": {
     "__type__": "bcQuat",
     "__typeHash__": 3955716320,
     "x": -0.09422311931848526,
     "y": 0.16996681690216064,
     "z": 0.9471209645271301,
     "w": 0.2553335130214691
    },
    "wp": {
     "x": 19.142900466918945,
     "y": 11.93529987335205,
     "z": 5.931049823760986
    }
   },
   "snoname": {
    "__raw__": 457255,
    "__group__": 57,
    "__type__": "DT_SNO_NAME",
    "__typeHash__": 3339108615,
    "__targetFileName__": "base/meta/Material/Cave_Flooded_Mold_Tendrils_B.mat",
    "groupName": "Material",
    "name": "Cave_Flooded_Mold_Tendrils_B"
   },
   "dwMarkerFlags": 1024,
   "dwMarkerFlagsEx": 0,
   "vecScale": {
    "x": 1.2200000286102295,
    "y": 1.2200000286102295,
    "z": 1.2200000286102295
   },
   "ptBase": [
    {
     "__type__": "MarkerDecalData",
     "__typeHash__": 2650697781,
     "dwType": 2650697781,
     "dwPad": 0,
     "dwMarkerDecalFlags": 0,
     "flAngleThreshold": 3.1415927410125732,
     "unk_18f0908": 0,
     "bDieOverride": false,
     "ptRunTimeMaterialValues": []
    }
   ],
   "ptGroupData": [],
   "ptMarkerLinks": [],
   "unk_c339f69": -1,
   "dwSeed": 0,
   "tPrefabData": {
    "__type__": "PrefabData",
    "__typeHash__": 3988626058,
    "dwFlags": 0,
    "eOverrideFadeSettings": 0,
    "eFadeMethod": 0,
    "nFadeGroup": 0,
    "unk_d094b9a": 0,
    "eCullingLevel": 0,
    "szLookOverride": 0,
    "dwShaderMapOverride": 4294967295,
    "ptRunTimeMaterialValues": []
   }
  },
  {
   "__type__": "Marker",
   "__typeHash__": 3132676386,
   "dwHash": 3636573009,
   "nID": 439,
   "eType": 0,
   "transform": {
    "__type__": "PRTransform",
    "__typeHash__": 2588169118,
    "q": {
     "__type__": "bcQuat",
     "__typeHash__": 3955716320,
     "x": 0.17443519830703735,
     "y": 0.06894753873348236,
     "z": 0.9184632301330566,
     "w": 0.3482010066509247
    },
    "wp": {
     "x": 19.990800857543945,
     "y": 18.07670021057129,
     "z": 3.388390064239502
    }
   },
   "snoname": {
    "__raw__": 457255,
    "__group__": 57,
    "__type__": "DT_SNO_NAME",
    "__typeHash__": 3339108615,
    "__targetFileName__": "base/meta/Material/Cave_Flooded_Mold_Tendrils_B.mat",
    "groupName": "Material",
    "name": "Cave_Flooded_Mold_Tendrils_B"
   },
   "dwMarkerFlags": 1024,
   "dwMarkerFlagsEx": 0,
   "vecScale": {
    "x": 1.2200000286102295,
    "y": 1.2200000286102295,
    "z": 1.2200000286102295
   },
   "ptBase": [
    {
     "__type__": "MarkerDecalData",
     "__typeHash__": 2650697781,
     "dwType": 2650697781,
     "dwPad": 0,
     "dwMarkerDecalFlags": 0,
     "flAngleThreshold": 3.1415927410125732,
     "unk_18f0908": 0,
     "bDieOverride": false,
     "ptRunTimeMaterialValues": []
    }
   ],
   "ptGroupData": [],
   "ptMarkerLinks": [],
   "unk_c339f69": -1,
   "dwSeed": 0,
   "tPrefabData": {
    "__type__": "PrefabData",
    "__typeHash__": 3988626058,
    "dwFlags": 0,
    "eOverrideFadeSettings": 0,
    "eFadeMethod": 0,
    "nFadeGroup": 0,
    "unk_d094b9a": 0,
    "eCullingLevel": 0,
    "szLookOverride": 0,
    "dwShaderMapOverride": 4294967295,
    "ptRunTimeMaterialValues": []
   }
  },
  {
   "__type__": "Marker",
   "__typeHash__": 3132676386,
   "dwHash": 3636573010,
   "nID": 440,
   "eType": 0,
   "transform": {
    "__type__": "PRTransform",
    "__typeHash__": 2588169118,
    "q": {
     "__type__": "bcQuat",
     "__typeHash__": 3955716320,
     "x": 0.005394001491367817,
     "y": 0.09229246526956558,
     "z": 0.9471025466918945,
     "w": 0.3073270916938782
    },
    "wp": {
     "x": 19.88789939880371,
     "y": 20.8031005859375,
     "z": 2.4640700817108154
    }
   },
   "snoname": {
    "__raw__": 457255,
    "__group__": 57,
    "__type__": "DT_SNO_NAME",
    "__typeHash__": 3339108615,
    "__targetFileName__": "base/meta/Material/Cave_Flooded_Mold_Tendrils_B.mat",
    "groupName": "Material",
    "name": "Cave_Flooded_Mold_Tendrils_B"
   },
   "dwMarkerFlags": 1024,
   "dwMarkerFlagsEx": 0,
   "vecScale": {
    "x": 1.2200000286102295,
    "y": 1.2200000286102295,
    "z": 1.2200000286102295
   },
   "ptBase": [
    {
     "__type__": "MarkerDecalData",
     "__typeHash__": 2650697781,
     "dwType": 2650697781,
     "dwPad": 0,
     "dwMarkerDecalFlags": 0,
     "flAngleThreshold": 3.1415927410125732,
     "unk_18f0908": 0,
     "bDieOverride": false,
     "ptRunTimeMaterialValues": []
    }
   ],
   "ptGroupData": [],
   "ptMarkerLinks": [],
   "unk_c339f69": -1,
   "dwSeed": 0,
   "tPrefabData": {
    "__type__": "PrefabData",
    "__typeHash__": 3988626058,
    "dwFlags": 0,
    "eOverrideFadeSettings": 0,
    "eFadeMethod": 0,
    "nFadeGroup": 0,
    "unk_d094b9a": 0,
    "eCullingLevel": 0,
    "szLookOverride": 0,
    "dwShaderMapOverride": 4294967295,
    "ptRunTimeMaterialValues": []
   }
  },
  {
   "__type__": "Marker",
   "__typeHash__": 3132676386,
   "dwHash": 3636573011,
   "nID": 441,
   "eType": 0,
   "transform": {
    "__type__": "PRTransform",
    "__typeHash__": 2588169118,
    "q": {
     "__type__": "bcQuat",
     "__typeHash__": 3955716320,
     "x": 0.16768302023410797,
     "y": 0.18568773567676544,
     "z": 0.6014707684516907,
     "w": 0.7587065100669861
    },
    "wp": {
     "x": 12.81659984588623,
     "y": 24.39299964904785,
     "z": 1.115149974822998
    }
   },
   "snoname": {
    "__raw__": 457255,
    "__group__": 57,
    "__type__": "DT_SNO_NAME",
    "__typeHash__": 3339108615,
    "__targetFileName__": "base/meta/Material/Cave_Flooded_Mold_Tendrils_B.mat",
    "groupName": "Material",
    "name": "Cave_Flooded_Mold_Tendrils_B"
   },
   "dwMarkerFlags": 1024,
   "dwMarkerFlagsEx": 0,
   "vecScale": {
    "x": 1.2200000286102295,
    "y": 1.2200000286102295,
    "z": 1.2200000286102295
   },
   "ptBase": [
    {
     "__type__": "MarkerDecalData",
     "__typeHash__": 2650697781,
     "dwType": 2650697781,
     "dwPad": 0,
     "dwMarkerDecalFlags": 0,
     "flAngleThreshold": 3.1415927410125732,
     "unk_18f0908": 0,
     "bDieOverride": false,
     "ptRunTimeMaterialValues": []
    }
   ],
   "ptGroupData": [],
   "ptMarkerLinks": [],
   "unk_c339f69": -1,
   "dwSeed": 0,
   "tPrefabData": {
    "__type__": "PrefabData",
    "__typeHash__": 3988626058,
    "dwFlags": 0,
    "eOverrideFadeSettings": 0,
    "eFadeMethod": 0,
    "nFadeGroup": 0,
    "unk_d094b9a": 0,
    "eCullingLevel": 0,
    "szLookOverride": 0,
    "dwShaderMapOverride": 4294967295,
    "ptRunTimeMaterialValues": []
   }
  },
  {
   "__type__": "Marker",
   "__typeHash__": 3132676386,
   "dwHash": 3636573035,
   "nID": 442,
   "eType": 0,
   "transform": {
    "__type__": "PRTransform",
    "__typeHash__": 2588169118,
    "q": {
     "__type__": "bcQuat",
     "__typeHash__": 3955716320,
     "x": -0.23315663635730743,
     "y": -0.05964674428105354,
     "z": 0.9578292965888977,
     "w": 0.15698209404945374
    },
    "wp": {
     "x": 18.29840087890625,
     "y": 29.566999435424805,
     "z": 0.4567370116710663
    }
   },
   "snoname": {
    "__raw__": 457255,
    "__group__": 57,
    "__type__": "DT_SNO_NAME",
    "__typeHash__": 3339108615,
    "__targetFileName__": "base/meta/Material/Cave_Flooded_Mold_Tendrils_B.mat",
    "groupName": "Material",
    "name": "Cave_Flooded_Mold_Tendrils_B"
   },
   "dwMarkerFlags": 1024,
   "dwMarkerFlagsEx": 0,
   "vecScale": {
    "x": 1.2200000286102295,
    "y": 1.2200000286102295,
    "z": 1.2200000286102295
   },
   "ptBase": [
    {
     "__type__": "MarkerDecalData",
     "__typeHash__": 2650697781,
     "dwType": 2650697781,
     "dwPad": 0,
     "dwMarkerDecalFlags": 0,
     "flAngleThreshold": 3.1415927410125732,
     "unk_18f0908": 0,
     "bDieOverride": false,
     "ptRunTimeMaterialValues": []
    }
   ],
   "ptGroupData": [],
   "ptMarkerLinks": [],
   "unk_c339f69": -1,
   "dwSeed": 0,
   "tPrefabData": {
    "__type__": "PrefabData",
    "__typeHash__": 3988626058,
    "dwFlags": 0,
    "eOverrideFadeSettings": 0,
    "eFadeMethod": 0,
    "nFadeGroup": 0,
    "unk_d094b9a": 0,
    "eCullingLevel": 0,
    "szLookOverride": 0,
    "dwShaderMapOverride": 4294967295,
    "ptRunTimeMaterialValues": []
   }
  },
  {
   "__type__": "Marker",
   "__typeHash__": 3132676386,
   "dwHash": 3636573036,
   "nID": 443,
   "eType": 0,
   "transform": {
    "__type__": "PRTransform",
    "__typeHash__": 2588169118,
    "q": {
     "__type__": "bcQuat",
     "__typeHash__": 3955716320,
     "x": -0.01730126142501831,
     "y": -0.0918244943022728,
     "z": 0.9533844590187073,
     "w": 0.286926805973053
    },
    "wp": {
     "x": 21.62529945373535,
     "y": 25.82390022277832,
     "z": 2.1174399852752686
    }
   },
   "snoname": {
    "__raw__": 457255,
    "__group__": 57,
    "__type__": "DT_SNO_NAME",
    "__typeHash__": 3339108615,
    "__targetFileName__": "base/meta/Material/Cave_Flooded_Mold_Tendrils_B.mat",
    "groupName": "Material",
    "name": "Cave_Flooded_Mold_Tendrils_B"
   },
   "dwMarkerFlags": 1024,
   "dwMarkerFlagsEx": 0,
   "vecScale": {
    "x": 1.2200000286102295,
    "y": 1.2200000286102295,
    "z": 1.2200000286102295
   },
   "ptBase": [
    {
     "__type__": "MarkerDecalData",
     "__typeHash__": 2650697781,
     "dwType": 2650697781,
     "dwPad": 0,
     "dwMarkerDecalFlags": 0,
     "flAngleThreshold": 3.1415927410125732,
     "unk_18f0908": 0,
     "bDieOverride": false,
     "ptRunTimeMaterialValues": []
    }
   ],
   "ptGroupData": [],
   "ptMarkerLinks": [],
   "unk_c339f69": -1,
   "dwSeed": 0,
   "tPrefabData": {
    "__type__": "PrefabData",
    "__typeHash__": 3988626058,
    "dwFlags": 0,
    "eOverrideFadeSettings": 0,
    "eFadeMethod": 0,
    "nFadeGroup": 0,
    "unk_d094b9a": 0,
    "eCullingLevel": 0,
    "szLookOverride": 0,
    "dwShaderMapOverride": 4294967295,
    "ptRunTimeMaterialValues": []
   }
  },
  {
   "__type__": "Marker",
   "__typeHash__": 3132676386,
   "dwHash": 3636573037,
   "nID": 444,
   "eType": 0,
   "transform": {
    "__type__": "PRTransform",
    "__typeHash__": 2588169118,
    "q": {
     "__type__": "bcQuat",
     "__typeHash__": 3955716320,
     "x": -0.07030177861452103,
     "y": 0.007095948327332735,
     "z": 0.9594930410385132,
     "w": 0.2727278470993042
    },
    "wp": {
     "x": 24.370100021362305,
     "y": 23.42889976501465,
     "z": 3.843440055847168
    }
   },
   "snoname": {
    "__raw__": 457255,
    "__group__": 57,
    "__type__": "DT_SNO_NAME",
    "__typeHash__": 3339108615,
    "__targetFileName__": "base/meta/Material/Cave_Flooded_Mold_Tendrils_B.mat",
    "groupName": "Material",
    "name": "Cave_Flooded_Mold_Tendrils_B"
   },
   "dwMarkerFlags": 1024,
   "dwMarkerFlagsEx": 0,
   "vecScale": {
    "x": 1.2200000286102295,
    "y": 1.2200000286102295,
    "z": 1.2200000286102295
   },
   "ptBase": [
    {
     "__type__": "MarkerDecalData",
     "__typeHash__": 2650697781,
     "dwType": 2650697781,
     "dwPad": 0,
     "dwMarkerDecalFlags": 0,
     "flAngleThreshold": 3.1415927410125732,
     "unk_18f0908": 0,
     "bDieOverride": false,
     "ptRunTimeMaterialValues": []
    }
   ],
   "ptGroupData": [],
   "ptMarkerLinks": [],
   "unk_c339f69": -1,
   "dwSeed": 0,
   "tPrefabData": {
    "__type__": "PrefabData",
    "__typeHash__": 3988626058,
    "dwFlags": 0,
    "eOverrideFadeSettings": 0,
    "eFadeMethod": 0,
    "nFadeGroup": 0,
    "unk_d094b9a": 0,
    "eCullingLevel": 0,
    "szLookOverride": 0,
    "dwShaderMapOverride": 4294967295,
    "ptRunTimeMaterialValues": []
   }
  },
  {
   "__type__": "Marker",
   "__typeHash__": 3132676386,
   "dwHash": 349088425,
   "nID": 451,
   "eType": 0,
   "transform": {
    "__type__": "PRTransform",
    "__typeHash__": 2588169118,
    "q": {
     "__type__": "bcQuat",
     "__typeHash__": 3955716320,
     "x": -0.2078416794538498,
     "y": -0.04494369402527809,
     "z": -0.36716023087501526,
     "w": 0.9055249094963074
    },
    "wp": {
     "x": 20.408899307250977,
     "y": 19.565799713134766,
     "z": 2.856410026550293
    }
   },
   "snoname": {
    "__raw__": 457252,
    "__group__": 57,
    "__type__": "DT_SNO_NAME",
    "__typeHash__": 3339108615,
    "__targetFileName__": "base/meta/Material/Cave_Flooded_Mold_Tendrils_A_01.mat",
    "groupName": "Material",
    "name": "Cave_Flooded_Mold_Tendrils_A_01"
   },
   "dwMarkerFlags": 1024,
   "dwMarkerFlagsEx": 0,
   "vecScale": {
    "x": 1,
    "y": 1,
    "z": 1
   },
   "ptBase": [
    {
     "__type__": "MarkerDecalData",
     "__typeHash__": 2650697781,
     "dwType": 2650697781,
     "dwPad": 0,
     "dwMarkerDecalFlags": 0,
     "flAngleThreshold": 3.1415927410125732,
     "unk_18f0908": 0,
     "bDieOverride": false,
     "ptRunTimeMaterialValues": []
    }
   ],
   "ptGroupData": [],
   "ptMarkerLinks": [],
   "unk_c339f69": -1,
   "dwSeed": 0,
   "tPrefabData": {
    "__type__": "PrefabData",
    "__typeHash__": 3988626058,
    "dwFlags": 0,
    "eOverrideFadeSettings": 0,
    "eFadeMethod": 0,
    "nFadeGroup": 0,
    "unk_d094b9a": 0,
    "eCullingLevel": 0,
    "szLookOverride": 0,
    "dwShaderMapOverride": 4294967295,
    "ptRunTimeMaterialValues": []
   }
  },
  {
   "__type__": "Marker",
   "__typeHash__": 3132676386,
   "dwHash": 349088426,
   "nID": 452,
   "eType": 0,
   "transform": {
    "__type__": "PRTransform",
    "__typeHash__": 2588169118,
    "q": {
     "__type__": "bcQuat",
     "__typeHash__": 3955716320,
     "x": -0.025985755026340485,
     "y": 0.24971508979797363,
     "z": -0.22298124432563782,
     "w": 0.9419376254081726
    },
    "wp": {
     "x": 11.863699913024902,
     "y": 27.382099151611328,
     "z": 0.42549100518226624
    }
   },
   "snoname": {
    "__raw__": 457252,
    "__group__": 57,
    "__type__": "DT_SNO_NAME",
    "__typeHash__": 3339108615,
    "__targetFileName__": "base/meta/Material/Cave_Flooded_Mold_Tendrils_A_01.mat",
    "groupName": "Material",
    "name": "Cave_Flooded_Mold_Tendrils_A_01"
   },
   "dwMarkerFlags": 1024,
   "dwMarkerFlagsEx": 0,
   "vecScale": {
    "x": 1,
    "y": 1,
    "z": 1
   },
   "ptBase": [
    {
     "__type__": "MarkerDecalData",
     "__typeHash__": 2650697781,
     "dwType": 2650697781,
     "dwPad": 0,
     "dwMarkerDecalFlags": 0,
     "flAngleThreshold": 3.1415927410125732,
     "unk_18f0908": 0,
     "bDieOverride": false,
     "ptRunTimeMaterialValues": []
    }
   ],
   "ptGroupData": [],
   "ptMarkerLinks": [],
   "unk_c339f69": -1,
   "dwSeed": 0,
   "tPrefabData": {
    "__type__": "PrefabData",
    "__typeHash__": 3988626058,
    "dwFlags": 0,
    "eOverrideFadeSettings": 0,
    "eFadeMethod": 0,
    "nFadeGroup": 0,
    "unk_d094b9a": 0,
    "eCullingLevel": 0,
    "szLookOverride": 0,
    "dwShaderMapOverride": 4294967295,
    "ptRunTimeMaterialValues": []
   }
  },
  {
   "__type__": "Marker",
   "__typeHash__": 3132676386,
   "dwHash": 349088427,
   "nID": 453,
   "eType": 0,
   "transform": {
    "__type__": "PRTransform",
    "__typeHash__": 2588169118,
    "q": {
     "__type__": "bcQuat",
     "__typeHash__": 3955716320,
     "x": 0.024854442104697227,
     "y": -0.018890244886279106,
     "z": 0.17783841490745544,
     "w": 0.9835643768310547
    },
    "wp": {
     "x": 17.4325008392334,
     "y": 8.32748031616211,
     "z": 7.664599895477295
    }
   },
   "snoname": {
    "__raw__": 457252,
    "__group__": 57,
    "__type__": "DT_SNO_NAME",
    "__typeHash__": 3339108615,
    "__targetFileName__": "base/meta/Material/Cave_Flooded_Mold_Tendrils_A_01.mat",
    "groupName": "Material",
    "name": "Cave_Flooded_Mold_Tendrils_A_01"
   },
   "dwMarkerFlags": 1024,
   "dwMarkerFlagsEx": 0,
   "vecScale": {
    "x": 1,
    "y": 1,
    "z": 1
   },
   "ptBase": [
    {
     "__type__": "MarkerDecalData",
     "__typeHash__": 2650697781,
     "dwType": 2650697781,
     "dwPad": 0,
     "dwMarkerDecalFlags": 0,
     "flAngleThreshold": 3.1415927410125732,
     "unk_18f0908": 0,
     "bDieOverride": false,
     "ptRunTimeMaterialValues": []
    }
   ],
   "ptGroupData": [],
   "ptMarkerLinks": [],
   "unk_c339f69": -1,
   "dwSeed": 0,
   "tPrefabData": {
    "__type__": "PrefabData",
    "__typeHash__": 3988626058,
    "dwFlags": 0,
    "eOverrideFadeSettings": 0,
    "eFadeMethod": 0,
    "nFadeGroup": 0,
    "unk_d094b9a": 0,
    "eCullingLevel": 0,
    "szLookOverride": 0,
    "dwShaderMapOverride": 4294967295,
    "ptRunTimeMaterialValues": []
   }
  },
  {
   "__type__": "Marker",
   "__typeHash__": 3132676386,
   "dwHash": 3636573038,
   "nID": 464,
   "eType": 0,
   "transform": {
    "__type__": "PRTransform",
    "__typeHash__": 2588169118,
    "q": {
     "__type__": "bcQuat",
     "__typeHash__": 3955716320,
     "x": 0.17628219723701477,
     "y": 0.15873675048351288,
     "z": 0.7273635268211365,
     "w": 0.6439484357833862
    },
    "wp": {
     "x": 12.937700271606445,
     "y": 0.9135339856147766,
     "z": 9.2295503616333
    }
   },
   "snoname": {
    "__raw__": 457255,
    "__group__": 57,
    "__type__": "DT_SNO_NAME",
    "__typeHash__": 3339108615,
    "__targetFileName__": "base/meta/Material/Cave_Flooded_Mold_Tendrils_B.mat",
    "groupName": "Material",
    "name": "Cave_Flooded_Mold_Tendrils_B"
   },
   "dwMarkerFlags": 1024,
   "dwMarkerFlagsEx": 0,
   "vecScale": {
    "x": 1.2200000286102295,
    "y": 1.2200000286102295,
    "z": 1.2200000286102295
   },
   "ptBase": [
    {
     "__type__": "MarkerDecalData",
     "__typeHash__": 2650697781,
     "dwType": 2650697781,
     "dwPad": 0,
     "dwMarkerDecalFlags": 0,
     "flAngleThreshold": 3.1415927410125732,
     "unk_18f0908": 0,
     "bDieOverride": false,
     "ptRunTimeMaterialValues": []
    }
   ],
   "ptGroupData": [],
   "ptMarkerLinks": [],
   "unk_c339f69": -1,
   "dwSeed": 0,
   "tPrefabData": {
    "__type__": "PrefabData",
    "__typeHash__": 3988626058,
    "dwFlags": 0,
    "eOverrideFadeSettings": 0,
    "eFadeMethod": 0,
    "nFadeGroup": 0,
    "unk_d094b9a": 0,
    "eCullingLevel": 0,
    "szLookOverride": 0,
    "dwShaderMapOverride": 4294967295,
    "ptRunTimeMaterialValues": []
   }
  }
 ],
 "dwMarkerSetFlags": 262661,
 "nLabel": null,
 "snoCampaignEnableCondition": null,
 "arPrefabDataInfo": [],
 "ptPrefabDataMap": "0",
 "ptChunks": [
  {
   "__type__": "MarkerInstanceChunk",
   "__typeHash__": 2046453424,
   "ptInstanceGroups": {
    "__type__": "DT_VARIABLEARRAY",
    "__typeHash__": 3244749660,
    "__flags__": 2097152,
    "__external__": true,
    "value": {
     "__typeHash__": 2051550180,
     "__type__": "MarkerInstanceGroup",
     "dataOffset": 32,
     "dataSize": 72
    }
   },
   "tVertexAO": {
    "__type__": "MarkerInstanceGroupsAO",
    "__typeHash__": 3445310279,
    "arVertexAO": {
     "__type__": "DT_VARIABLEARRAY",
     "__typeHash__": 3244749660,
     "__flags__": 2097153,
     "__external__": true,
     "value": {
      "__typeHash__": 1028015787,
      "__type__": "DT_BYTE",
      "dataOffset": 256,
      "dataSize": 1688
     }
    }
   },
   "unk_2f217b0": 0,
   "aabbBounds": {
    "__type__": "AABB",
    "__typeHash__": 2408934,
    "wp": {
     "x": -1.6822333335876465,
     "y": 10.986292839050293,
     "z": 1.3743796348571777
    },
    "wvExt": {
     "x": 5.109912395477295,
     "y": 6.1414384841918945,
     "z": 7.16093111038208
    }
   }
  },
  {
   "__type__": "MarkerInstanceChunk",
   "__typeHash__": 2046453424,
   "ptInstanceGroups": {
    "__type__": "DT_VARIABLEARRAY",
    "__typeHash__": 3244749660,
    "__flags__": 2097152,
    "__external__": true,
    "value": {
     "__typeHash__": 2051550180,
     "__type__": "MarkerInstanceGroup",
     "dataOffset": 1944,
     "dataSize": 1800
    }
   },
   "tVertexAO": {
    "__type__": "MarkerInstanceGroupsAO",
    "__typeHash__": 3445310279,
    "arVertexAO": {
     "__type__": "DT_VARIABLEARRAY",
     "__typeHash__": 3244749660,
     "__flags__": 2097153,
     "__external__": true,
     "value": {
      "__typeHash__": 1028015787,
      "__type__": "DT_BYTE",
      "dataOffset": 13672,
      "dataSize": 131176
     }
    }
   },
   "unk_2f217b0": 0,
   "aabbBounds": {
    "__type__": "AABB",
    "__typeHash__": 2408934,
    "wp": {
     "x": 7.010883331298828,
     "y": 8.932774543762207,
     "z": 4.981899261474609
    },
    "wvExt": {
     "x": 11.283275604248047,
     "y": 10.196661949157715,
     "z": 10.221197128295898
    }
   }
  },
  {
   "__type__": "MarkerInstanceChunk",
   "__typeHash__": 2046453424,
   "ptInstanceGroups": {
    "__type__": "DT_VARIABLEARRAY",
    "__typeHash__": 3244749660,
    "__flags__": 2097152,
    "__external__": true,
    "value": {
     "__typeHash__": 2051550180,
     "__type__": "MarkerInstanceGroup",
     "dataOffset": 144848,
     "dataSize": 1728
    }
   },
   "tVertexAO": {
    "__type__": "MarkerInstanceGroupsAO",
    "__typeHash__": 3445310279,
    "arVertexAO": {
     "__type__": "DT_VARIABLEARRAY",
     "__typeHash__": 3244749660,
     "__flags__": 2097153,
     "__external__": true,
     "value": {
      "__typeHash__": 1028015787,
      "__type__": "DT_BYTE",
      "dataOffset": 156664,
      "dataSize": 147504
     }
    }
   },
   "unk_2f217b0": 0,
   "aabbBounds": {
    "__type__": "AABB",
    "__typeHash__": 2408934,
    "wp": {
     "x": 23.322948455810547,
     "y": 7.998317718505859,
     "z": 6.351034164428711
    },
    "wvExt": {
     "x": 9.78549575805664,
     "y": 10.463542938232422,
     "z": 8.950783729553223
    }
   }
  },
  {
   "__type__": "MarkerInstanceChunk",
   "__typeHash__": 2046453424,
   "ptInstanceGroups": {
    "__type__": "DT_VARIABLEARRAY",
    "__typeHash__": 3244749660,
    "__flags__": 2097152,
    "__external__": true,
    "value": {
     "__typeHash__": 2051550180,
     "__type__": "MarkerInstanceGroup",
     "dataOffset": 304168,
     "dataSize": 1368
    }
   },
   "tVertexAO": {
    "__type__": "MarkerInstanceGroupsAO",
    "__typeHash__": 3445310279,
    "arVertexAO": {
     "__type__": "DT_VARIABLEARRAY",
     "__typeHash__": 3244749660,
     "__flags__": 2097153,
     "__external__": true,
     "value": {
      "__typeHash__": 1028015787,
      "__type__": "DT_BYTE",
      "dataOffset": 311744,
      "dataSize": 73736
     }
    }
   },
   "unk_2f217b0": 0,
   "aabbBounds": {
    "__type__": "AABB",
    "__typeHash__": 2408934,
    "wp": {
     "x": 8.9729642868042,
     "y": 23.20724868774414,
     "z": 5.902492523193359
    },
    "wvExt": {
     "x": 8.69483470916748,
     "y": 11.070770263671875,
     "z": 9.504511833190918
    }
   }
  },
  {
   "__type__": "MarkerInstanceChunk",
   "__typeHash__": 2046453424,
   "ptInstanceGroups": {
    "__type__": "DT_VARIABLEARRAY",
    "__typeHash__": 3244749660,
    "__flags__": 2097152,
    "__external__": true,
    "value": {
     "__typeHash__": 2051550180,
     "__type__": "MarkerInstanceGroup",
     "dataOffset": 385480,
     "dataSize": 1584
    }
   },
   "tVertexAO": {
    "__type__": "MarkerInstanceGroupsAO",
    "__typeHash__": 3445310279,
    "arVertexAO": {
     "__type__": "DT_VARIABLEARRAY",
     "__typeHash__": 3244749660,
     "__flags__": 2097153,
     "__external__": true,
     "value": {
      "__typeHash__": 1028015787,
      "__type__": "DT_BYTE",
      "dataOffset": 394640,
      "dataSize": 132152
     }
    }
   },
   "unk_2f217b0": 0,
   "aabbBounds": {
    "__type__": "AABB",
    "__typeHash__": 2408934,
    "wp": {
     "x": 23.163265228271484,
     "y": 22.776535034179688,
     "z": 4.864381790161133
    },
    "wvExt": {
     "x": 9.446380615234375,
     "y": 10.99557113647461,
     "z": 8.838260650634766
    }
   }
  }
 ],
 "arVertexAOOffsets": [],
 "ptMergedMsgTriggeredEvents": [],
 "unk_2bbd1d": {
  "__type__": "Type_c8d78ce7",
  "__typeHash__": 3369569511,
  "nWidth": 0,
  "nHeight": 0,
  "nDepth": 0,
  "dwPitch": 0,
  "dwSlicePitch": 0,
  "flGridSize": 0,
  "wpOrigin": {
   "x": 0,
   "y": 0,
   "z": 0
  },
  "unk_4b236f4": "0",
  "unk_aa0958e": {
   "__type__": "DT_VARIABLEARRAY",
   "__typeHash__": 3244749660,
   "__flags__": 2097153,
   "__external__": true,
   "value": {
    "__typeHash__": 1028759507,
    "__type__": "DT_WORD",
    "dataOffset": 0,
    "dataSize": 0
   }
  },
  "unk_aa09583": {
   "__type__": "DT_VARIABLEARRAY",
   "__typeHash__": 3244749660,
   "__flags__": 2097153,
   "__external__": true,
   "value": {
    "__typeHash__": 1028759507,
    "__type__": "DT_WORD",
    "dataOffset": 0,
    "dataSize": 0
   }
  },
  "unk_aa0957e": {
   "__type__": "DT_VARIABLEARRAY",
   "__typeHash__": 3244749660,
   "__flags__": 2097153,
   "__external__": true,
   "value": {
    "__typeHash__": 1028759507,
    "__type__": "DT_WORD",
    "dataOffset": 0,
    "dataSize": 0
   }
  },
  "unk_dd3cf4b": {
   "__type__": "DT_VARIABLEARRAY",
   "__typeHash__": 3244749660,
   "__flags__": 2097153,
   "__external__": true,
   "value": {
    "__typeHash__": 1028759507,
    "__type__": "DT_WORD",
    "dataOffset": 0,
    "dataSize": 0
   }
  },
  "unk_dd3cf40": {
   "__type__": "DT_VARIABLEARRAY",
   "__typeHash__": 3244749660,
   "__flags__": 2097153,
   "__external__": true,
   "value": {
    "__typeHash__": 1028759507,
    "__type__": "DT_WORD",
    "dataOffset": 0,
    "dataSize": 0
   }
  },
  "unk_dd3cf3b": {
   "__type__": "DT_VARIABLEARRAY",
   "__typeHash__": 3244749660,
   "__flags__": 2097153,
   "__external__": true,
   "value": {
    "__typeHash__": 1028759507,
    "__type__": "DT_WORD",
    "dataOffset": 0,
    "dataSize": 0
   }
  }
 },
 "arVertexAO": {
  "__type__": "DT_VARIABLEARRAY",
  "__typeHash__": 3244749660,
  "__flags__": 2097152,
  "__external__": true,
  "value": {
   "__typeHash__": 1028015787,
   "__type__": "DT_BYTE",
   "dataOffset": 0,
   "dataSize": 0
  }
 },
 "unk_2f217b0": -1,
 "ptPrefabAOMap": "0"
}
